ansys/platform/instancemanagement/__init__.py
ansys/platform/instancemanagement/client.py
ansys/platform/instancemanagement/configuration.py
ansys/platform/instancemanagement/definition.py
ansys/platform/instancemanagement/exceptions.py
ansys/platform/instancemanagement/instance.py
ansys/platform/instancemanagement/interceptor.py
ansys/platform/instancemanagement/service.py
ansys_platform_instancemanagement-1.1.1.dist-info/LICENSE
ansys_platform_instancemanagement-1.1.1.dist-info/WHEEL
ansys_platform_instancemanagement-1.1.1.dist-info/METADATA
ansys_platform_instancemanagement-1.1.1.dist-info/RECORD
