Metadata-Version: 2.1
Name: ansys-platform-instancemanagement
Version: 1.1.1
Summary: A Python wrapper for Ansys platform instancemanagement
Author-email: "ANSYS, Inc." <pyansys.support@ansys.com>
Maintainer-email: PyAnsys developers <pyansys.maintainers@ansys.com>
Requires-Python: >=3.7
Classifier: Development Status :: 4 - Beta
Classifier: Programming Language :: Python :: 3
Classifier: License :: OSI Approved :: MIT License
Classifier: Operating System :: OS Independent
Requires-Dist: importlib-metadata >=4.0
Requires-Dist: ansys-api-platform-instancemanagement>=1.0.0b3
Project-URL: Source, https://github.com/pyansys/pypim
